{
  "updatedAt": "2026.04.29 10:29 KST (자동 업데이트)",
  "items": [
    {
      "symbol": "SOXL",
      "p1d": "-11.21%",
      "p1w": "+11.69%",
      "p1m": "+135.06%",
      "mdd": "-14.62%",
      "updatedAt": "2026.04.29"
    },
    {
      "symbol": "TQQQ",
      "p1d": "-3.03%",
      "p1w": "+5.82%",
      "p1m": "+56.63%",
      "mdd": "-3.03%",
      "updatedAt": "2026.04.29"
    },
    {
      "symbol": "SSO",
      "p1d": "-0.99%",
      "p1w": "+2.01%",
      "p1m": "+25.15%",
      "mdd": "-0.99%",
      "updatedAt": "2026.04.29"
    }
  ],
  "flow": {
    "updatedAt": "2026.04.29 10:29 KST (자동 업데이트)",
    "items": [
      {
        "id": "usdjpy",
        "label": "엔캐리 압력",
        "value": "USDJPY 159.62",
        "delta": "+0.17%",
        "tone": "up"
      },
      {
        "id": "dxy",
        "label": "달러 유동성",
        "value": "DXY 98.66",
        "delta": "+0.04%",
        "tone": "up"
      },
      {
        "id": "qqq_tlt",
        "label": "기관 프록시",
        "value": "QQQ/TLT 7.613",
        "delta": "-1.11%",
        "tone": "down"
      },
      {
        "id": "hyg_lqd",
        "label": "신용 체력",
        "value": "HYG/LQD 0.735",
        "delta": "-0.18%",
        "tone": "down"
      },
      {
        "id": "vix_hy",
        "label": "리스크 선호",
        "value": "VIX 17.83 / HY 2.84%",
        "delta": "VIX -0.19% · HY -0.02%",
        "tone": "up"
      }
    ],
    "regime": {
      "score": 58,
      "state": "Neutral",
      "action": "중립 비중 유지, 이벤트 확인 후 대응",
      "history": [
        {
          "d": "2026.04.28",
          "s": 90
        },
        {
          "d": "2026.04.29",
          "s": 58
        }
      ]
    }
  },
  "insight": {
    "sectorStrength": [
      {
        "id": "semiconductor",
        "label": "반도체",
        "symbol": "SOXX",
        "p1d": "-3.67%",
        "p1w": "+4.28%",
        "p1m": "+35.62%",
        "score": 16.8
      },
      {
        "id": "ai-growth",
        "label": "AI/성장",
        "symbol": "QQQ",
        "p1d": "-1.01%",
        "p1w": "+2.05%",
        "p1m": "+16.88%",
        "score": 8.1
      },
      {
        "id": "financials",
        "label": "금융",
        "symbol": "XLF",
        "p1d": "+0.08%",
        "p1w": "-0.86%",
        "p1m": "+8.45%",
        "score": 3.5
      },
      {
        "id": "energy",
        "label": "에너지",
        "symbol": "XLE",
        "p1d": "+1.66%",
        "p1w": "+3.29%",
        "p1m": "-7.75%",
        "score": -2
      }
    ],
    "weeklySummary": [
      "국면: Neutral (58/100) · 중립 비중 유지, 이벤트 확인 후 대응",
      "강세 섹터: 반도체(SOXX) +4.28% / +35.62%",
      "약세 섹터: 에너지(XLE) +3.29% / -7.75%"
    ]
  }
}
