{
  "updatedAt": "2026.05.31 09:15 KST (자동 업데이트)",
  "items": [
    {
      "label": "KOSPI",
      "value": "8,476.15",
      "delta": "+3.55%",
      "direction": "up"
    },
    {
      "label": "KOSDAQ",
      "value": "1,074.80",
      "delta": "-2.68%",
      "direction": "down"
    },
    {
      "label": "KOSPI200",
      "value": "1,342.82",
      "delta": "+3.89%",
      "direction": "up"
    },
    {
      "label": "DOW",
      "value": "51,032.46",
      "delta": "+0.72%",
      "direction": "up"
    },
    {
      "label": "S&P 500",
      "value": "7,580.06",
      "delta": "+0.22%",
      "direction": "up"
    },
    {
      "label": "Dollar Index",
      "value": "98.91",
      "delta": "-0.11%",
      "direction": "down"
    },
    {
      "label": "NASDAQ 100",
      "value": "30,333.18",
      "delta": "+0.36%",
      "direction": "up"
    },
    {
      "label": "USD/KRW",
      "value": "1,507.13",
      "delta": "+0.79%",
      "direction": "up"
    },
    {
      "label": "US 10Y",
      "value": "0.45%",
      "delta": "-0.04%p",
      "direction": "down"
    }
  ]
}
