{
  "updatedAt": "2026.06.13 03:09 KST (자동 업데이트)",
  "items": [
    {
      "label": "KOSPI",
      "value": "7,763.95",
      "delta": "+0.43%",
      "direction": "up"
    },
    {
      "label": "KOSDAQ",
      "value": "996.93",
      "delta": "+4.76%",
      "direction": "up"
    },
    {
      "label": "KOSPI200",
      "value": "1,231.54",
      "delta": "+0.36%",
      "direction": "up"
    },
    {
      "label": "DOW",
      "value": "50,848.75",
      "delta": "+1.86%",
      "direction": "up"
    },
    {
      "label": "S&P 500",
      "value": "7,394.30",
      "delta": "+1.75%",
      "direction": "up"
    },
    {
      "label": "Dollar Index",
      "value": "99.86",
      "delta": "-0.09%",
      "direction": "down"
    },
    {
      "label": "NASDAQ 100",
      "value": "29,446.18",
      "delta": "+3.29%",
      "direction": "up"
    },
    {
      "label": "USD/KRW",
      "value": "1,518.32",
      "delta": "-0.44%",
      "direction": "down"
    },
    {
      "label": "US 10Y",
      "value": "0.45%",
      "delta": "-1.74%p",
      "direction": "down"
    }
  ]
}
