{
  "updatedAt": "2026.06.14 10:37 KST (자동 업데이트)",
  "items": [
    {
      "label": "KOSPI",
      "value": "8,123.62",
      "delta": "+4.63%",
      "direction": "up"
    },
    {
      "label": "KOSDAQ",
      "value": "1,029.05",
      "delta": "+3.22%",
      "direction": "up"
    },
    {
      "label": "KOSPI200",
      "value": "1,291.32",
      "delta": "+4.85%",
      "direction": "up"
    },
    {
      "label": "DOW",
      "value": "51,202.26",
      "delta": "+0.70%",
      "direction": "up"
    },
    {
      "label": "S&P 500",
      "value": "7,431.46",
      "delta": "+0.50%",
      "direction": "up"
    },
    {
      "label": "Dollar Index",
      "value": "99.75",
      "delta": "-0.11%",
      "direction": "down"
    },
    {
      "label": "NASDAQ 100",
      "value": "29,635.95",
      "delta": "+0.64%",
      "direction": "up"
    },
    {
      "label": "USD/KRW",
      "value": "1,517.89",
      "delta": "+0.03%",
      "direction": "up"
    },
    {
      "label": "US 10Y",
      "value": "0.45%",
      "delta": "+0.54%p",
      "direction": "up"
    }
  ]
}
