[
  {
    "symbol": "USDKRW",
    "price": 1506.51,
    "change": -0.42
  },
  {
    "symbol": "DOW",
    "price": 50579.7,
    "change": 0.58
  },
  {
    "symbol": "SP500",
    "price": 7473.47,
    "change": 0.37
  },
  {
    "symbol": "NASDAQ",
    "price": 29481.64,
    "change": 0.42
  },
  {
    "symbol": "DXY",
    "price": 99.32,
    "change": 0.13
  },
  {
    "symbol": "US10Y",
    "price": 0.46,
    "change": -0.61
  },
  {
    "symbol": "VIX",
    "price": 16.59,
    "change": -0.11
  }
]
